{
    "status": "COMPLETE",
    "results": {
        "bntest": [
            "crypto/dh/dh_check.c"
        ],
        "clienthellotest": [
            "crypto/dh/dh_check.c"
        ],
        "dhtest": [
            "crypto/dh/dh_check.c"
        ],
        "dsatest": [
            "crypto/dh/dh_check.c"
        ],
        "ecdhtest": [
            "crypto/dh/dh_check.c"
        ],
        "ecdsatest": [
            "crypto/dh/dh_check.c"
        ],
        "ectest": [
            "crypto/dh/dh_check.c"
        ],
        "enginetest": [
            "crypto/dh/dh_check.c"
        ],
        "evp_extra_test": [
            "crypto/dh/dh_check.c"
        ],
        "evp_test": [
            "crypto/dh/dh_check.c"
        ],
        "exptest": [
            "crypto/dh/dh_check.c"
        ],
        "hmactest": [
            "crypto/dh/dh_check.c"
        ],
        "igetest": [
            "crypto/dh/dh_check.c"
        ],
        "md4test": [
            "crypto/dh/dh_check.c"
        ],
        "md5test": [
            "crypto/dh/dh_check.c"
        ],
        "mdc2test": [
            "crypto/dh/dh_check.c"
        ],
        "randtest": [
            "crypto/dh/dh_check.c"
        ],
        "rmdtest": [
            "crypto/dh/dh_check.c"
        ],
        "rsa_test": [
            "crypto/dh/dh_check.c"
        ],
        "sha1test": [
            "crypto/dh/dh_check.c"
        ],
        "shatest": [
            "crypto/dh/dh_check.c"
        ],
        "srptest": [
            "crypto/dh/dh_check.c"
        ],
        "ssltest": [
            "crypto/dh/dh_check.c"
        ],
        "v3nametest": [
            "crypto/dh/dh_check.c"
        ],
        "verify_extra_test": [
            "crypto/dh/dh_check.c"
        ]
    }
}